[ {"PD5": {"title": "Project Management", "preq": "", "preq_note": "Prereq: COOP or EDGE students only", "antireq": null, "terms_offered": [], "units": 0.5}}, {"PD8": {"title": "Intercultural Skills", "preq": "", "preq_note": "Prereq: COOP or EDGE students only", "antireq": null, "terms_offered": [], "units": 0.5}}, {"PD1": {"title": "Career Fundamentals", "preq": "", "preq_note": "Prereq: Not open to Engineering students", "antireq": null, "terms_offered": [], "units": 0.5}}, {"PD3": {"title": "Communication", "preq": "", "preq_note": "Prereq: COOP or EDGE students only", "antireq": null, "terms_offered": [], "units": 0.5}}, {"PD9": {"title": "Ethical Decision Making", "preq": "", "preq_note": "Prereq: COOP or EDGE students only", "antireq": null, "terms_offered": [], "units": 0.5}}, {"PD20": {"title": "Engineering Workplace Skills I: Developing Reasoned Conclusions", "preq": "", "preq_note": "Prereq: Engineering students only", "antireq": null, "terms_offered": [], "units": 0.5}}, {"PD22": {"title": "Professionalism and Ethics in Engineering Practice", "preq": "", "preq_note": "Prereq: Co-op students only.", "antireq": "ECE 290", "terms_offered": [], "units": 0.5}}, {"PD2": {"title": "Critical Reflection and Report Writing", "preq": "", "preq_note": "Prereq: Co-op students only; Not open to Engineering students", "antireq": null, "terms_offered": [], "units": 0.5}}, {"PD4": {"title": "Teamwork", "preq": "", "preq_note": "Prereq: COOP or EDGE students only", "antireq": null, "terms_offered": [], "units": 0.5}}, {"PD7": {"title": "Conflict Resolution", "preq": "", "preq_note": "Prereq: COOP or EDGE students only", "antireq": null, "terms_offered": [], "units": 0.5}}, {"PD6": {"title": "Problem Solving", "preq": "", "preq_note": "Prereq: COOP or EDGE students only", "antireq": null, "terms_offered": [], "units": 0.5}}, {"PD21": {"title": "Engineering Workplace Skills II: Developing Effective Plans", "preq": "", "preq_note": "Prereq: Engineering students only", "antireq": null, "terms_offered": [], "units": 0.5}}]